test.py
fromless/__init__.py
fromless/demo.py
fromless/gtf.py
fromless-0.0.2.dist-info/licenses/LICENCE
fromless-0.0.2.dist-info/METADATA
fromless-0.0.2.dist-info/WHEEL
fromless-0.0.2.dist-info/top_level.txt
fromless-0.0.2.dist-info/RECORD
