Metadata-Version: 2.4
Name: fromless
Version: 0.0.2
Summary: A base class that prevents subclasses from being instantiated from an unqualified import.
Author-email: Christopher Neugebauer <_@chrisjrn.com>
License-Expression: MIT
Classifier: Programming Language :: Python :: 3
Classifier: Operating System :: OS Independent
Requires-Python: >=3.9
License-File: LICENCE
Dynamic: license-file
